MANIFEST.in
README.rst
setup.py
fusiontables/__init__.py
fusiontables/ftclient.py
fusiontables/authorization/__init__.py
fusiontables/authorization/clientlogin.py
fusiontables/authorization/oauth.py
fusiontables/fileimport/__init__.py
fusiontables/fileimport/fileimporter.py
fusiontables/sql/__init__.py
fusiontables/sql/sqlbuilder.py
python_fusiontables.egg-info/PKG-INFO
python_fusiontables.egg-info/SOURCES.txt
python_fusiontables.egg-info/dependency_links.txt
python_fusiontables.egg-info/requires.txt
python_fusiontables.egg-info/top_level.txt