Metadata-Version: 1.0
Name: python-fusiontables
Version: 0.1
Summary: Python client for Google Fusion Tables
Home-page: http://github.com/smn/python-fusiontables
Author: Simon de Haan
Author-email: simon@praekeltfoundation.org
License: MIT
Platform: UNKNOWN
